vezgo/__init__.py
vezgo/client.py
vezgo/constants.py
vezgo/exceptions.py
vezgo/resources/__init__.py
vezgo/resources/accounts.py
vezgo/resources/base.py
vezgo/resources/history.py
vezgo/resources/orders.py
vezgo/resources/providers.py
vezgo/resources/teams.py
vezgo/resources/transactions.py
vezgo-1.0.1.dist-info/licenses/LICENSE
vezgo-1.0.1.dist-info/METADATA
vezgo-1.0.1.dist-info/WHEEL
vezgo-1.0.1.dist-info/top_level.txt
vezgo-1.0.1.dist-info/RECORD
