Metadata-Version: 2.4
Name: vezgo
Version: 1.0.1
Summary: Official Vezgo Python SDK for Cryptocurrency Data API
Author-email: Vezgo <hello@vezgo.com>
Maintainer-email: Vezgo <hello@vezgo.com>
License-Expression: MIT
Project-URL: Homepage, https://vezgo.com
Project-URL: Documentation, https://vezgo.com/docs
Project-URL: Repository, https://github.com/wealthica/vezgo-sdk-python
Project-URL: Changelog, https://github.com/wealthica/vezgo-sdk-python/blob/main/CHANGELOG.md
Keywords: vezgo,cryptocurrency,crypto,api,sdk,bitcoin,ethereum,coinbase,binance,blockchain,wallet,exchange,portfolio,fintech
Classifier: Development Status :: 5 - Production/Stable
Classifier: Intended Audience :: Developers
Classifier: Operating System :: OS Independent
Classifier: Programming Language :: Python :: 3
Classifier: Programming Language :: Python :: 3.8
Classifier: Programming Language :: Python :: 3.9
Classifier: Programming Language :: Python :: 3.10
Classifier: Programming Language :: Python :: 3.11
Classifier: Programming Language :: Python :: 3.12
Classifier: Topic :: Software Development :: Libraries :: Python Modules
Classifier: Topic :: Office/Business :: Financial
Requires-Python: >=3.8
License-File: LICENSE
Requires-Dist: httpx>=0.24.0
Requires-Dist: pyjwt>=2.0.0
Provides-Extra: dev
Requires-Dist: pytest>=7.0.0; extra == "dev"
Requires-Dist: pytest-asyncio>=0.21.0; extra == "dev"
Requires-Dist: pytest-cov>=4.0.0; extra == "dev"
Requires-Dist: black>=23.0.0; extra == "dev"
Requires-Dist: isort>=5.12.0; extra == "dev"
Requires-Dist: mypy>=1.0.0; extra == "dev"
Requires-Dist: ruff>=0.1.0; extra == "dev"
Dynamic: license-file
